{"P3": {"labels": ["documentation", "Website", "Practicality"], "postTitle": "\u4f7f\u7528Github\u642d\u5efa\u4e2a\u4eba\u535a\u5ba2!", "postUrl": "post/shi-yong-Github-da-jian-ge-ren-bo-ke-%21.html", "createdDate": "2025-08-31", "dateLabelColor": "#0969da"}, "P1": {"labels": ["documentation", "Game"], "postTitle": "wards!?---kards\u7684\u3002\u5e73\u66ff\uff1f\uff0c", "postUrl": "post/wards%21----kards-de-%E3%80%82-ping-ti-%EF%BC%9F%EF%BC%8C.html", "createdDate": "2025-08-29", "dateLabelColor": "#0969da"}, "labelColorDict": {"bug": "#d73a4a", "documentation": "#0075ca", "duplicate": "#cfd3d7", "enhancement": "#a2eeef", "Game": "#aaaaaa", "good first issue": "#7057ff", "help wanted": "#008672", "invalid": "#e4e669", "Practicality": "#aaaaaa", "question": "#d876e3", "Website": "#aaaaaa", "wontfix": "#ffffff"}}